git_sanity/__init__.py
git_sanity/__main__.py
git_sanity/branch.py
git_sanity/cherry_pick.py
git_sanity/clone.py
git_sanity/command.py
git_sanity/cppcheck.py
git_sanity/fetch.py
git_sanity/init.py
git_sanity/measure.py
git_sanity/push.py
git_sanity/rebase.py
git_sanity/switch.py
git_sanity/sync.py
git_sanity/utils.py
git_sanity-3.0.2.dist-info/LICENSE.txt
git_sanity-3.0.2.dist-info/METADATA
git_sanity-3.0.2.dist-info/WHEEL
git_sanity-3.0.2.dist-info/entry_points.txt
git_sanity-3.0.2.dist-info/top_level.txt
git_sanity-3.0.2.dist-info/RECORD
