Metadata-Version: 2.1
Name: git-sanity
Version: 3.0.2
Summary: Manage multiple git repos with sanity
Home-page: https://github.com/yuqiaoyu/git-sanity
Author: yuqiaoyu
Author-email: yu_junqiang@qq.com
License: MIT
Keywords: git,manage multiple repositories,cui,command-line
Platform: linux
Platform: osx
Platform: win32
Classifier: Development Status :: 4 - Beta
Classifier: Intended Audience :: Developers
Classifier: License :: OSI Approved :: MIT License
Classifier: Operating System :: POSIX
Classifier: Operating System :: MacOS :: MacOS X
Classifier: Operating System :: Microsoft :: Windows
Classifier: Topic :: Software Development :: Version Control :: Git
Classifier: Topic :: Terminals
Classifier: Topic :: Utilities
Classifier: Programming Language :: Python :: 3.10
Classifier: Programming Language :: Python :: 3.11
Classifier: Programming Language :: Python :: 3.12
Requires-Python: ~=3.8
License-File: LICENSE.txt
Requires-Dist: argcomplete
Requires-Dist: certifi
Requires-Dist: charset-normalizer
Requires-Dist: idna
Requires-Dist: requests
Requires-Dist: urllib3
